__init__.py
bai2009.py
pyInteractiveFixedEffects-0.0.2.dist-info/LICENSE
pyInteractiveFixedEffects-0.0.2.dist-info/METADATA
pyInteractiveFixedEffects-0.0.2.dist-info/WHEEL
pyInteractiveFixedEffects-0.0.2.dist-info/top_level.txt
pyInteractiveFixedEffects-0.0.2.dist-info/RECORD
