Metadata-Version: 2.1
Name: pyInteractiveFixedEffects
Version: 0.0.2
Summary: Python implementation of the Interactive Fixed Effects estimator presented in Bai (2009).
Author-email: Javier Boncompte <jiboncom@gmail.com>
License: MIT License        
Project-URL: Homepage, https://github.com/jiboncom/pyInteractiveFixedEffects
Project-URL: Bug Tracker, https://github.com/jiboncom/pyInteractiveFixedEffects/issues
Classifier: Programming Language :: Python :: 3
Classifier: License :: OSI Approved :: MIT License
Classifier: Operating System :: OS Independent
Requires-Python: >=3.7
License-File: LICENSE
